examples/__init__.py
examples/centralized/__init__.py
examples/centralized/main.py
examples/cross_device/__init__.py
examples/cross_device/mqtt_s3_fedavg_cifar10_resnet20_example/__init__.py
examples/cross_device/mqtt_s3_fedavg_cifar10_resnet20_example/my_dataset.py
examples/cross_device/mqtt_s3_fedavg_cifar10_resnet20_example/torch_server.py
examples/cross_device/mqtt_s3_fedavg_mnist_lenet_example/__init__.py
examples/cross_device/mqtt_s3_fedavg_mnist_lenet_example/my_dataset.py
examples/cross_device/mqtt_s3_fedavg_mnist_lenet_example/torch_server.py
examples/cross_silo/__init__.py
examples/cross_silo/cuda_rpc_fedavg_mnist_lr_example/__init__.py
examples/cross_silo/cuda_rpc_fedavg_mnist_lr_example/one_line/__init__.py
examples/cross_silo/cuda_rpc_fedavg_mnist_lr_example/one_line/torch_client.py
examples/cross_silo/cuda_rpc_fedavg_mnist_lr_example/one_line/torch_server.py
examples/cross_silo/grpc_fedavg_mnist_lr_example/__init__.py
examples/cross_silo/grpc_fedavg_mnist_lr_example/custom_data_and_model/__init__.py
examples/cross_silo/grpc_fedavg_mnist_lr_example/custom_data_and_model/torch_client.py
examples/cross_silo/grpc_fedavg_mnist_lr_example/custom_data_and_model/torch_server.py
examples/cross_silo/grpc_fedavg_mnist_lr_example/one_line/__init__.py
examples/cross_silo/grpc_fedavg_mnist_lr_example/one_line/torch_client.py
examples/cross_silo/grpc_fedavg_mnist_lr_example/one_line/torch_server.py
examples/cross_silo/grpc_fedavg_mnist_lr_example/step_by_step/__init__.py
examples/cross_silo/grpc_fedavg_mnist_lr_example/step_by_step/torch_client.py
examples/cross_silo/grpc_fedavg_mnist_lr_example/step_by_step/torch_server.py
examples/cross_silo/grpc_tls_fedavg_mnist_lr_example/__init__.py
examples/cross_silo/grpc_tls_fedavg_mnist_lr_example/step_by_step/__init__.py
examples/cross_silo/grpc_tls_fedavg_mnist_lr_example/step_by_step/torch_client.py
examples/cross_silo/grpc_tls_fedavg_mnist_lr_example/step_by_step/torch_server.py
fedml_afaf-0.7.327.dist-info/LICENSE
fedml_afaf-0.7.327.dist-info/METADATA
fedml_afaf-0.7.327.dist-info/WHEEL
fedml_afaf-0.7.327.dist-info/entry_points.txt
fedml_afaf-0.7.327.dist-info/top_level.txt
fedml_afaf-0.7.327.dist-info/RECORD
