Metadata-Version: 2.1
Name: fedml-afaf
Version: 0.7.327
Summary: A research and production integrated edge-cloud library for federated/distributed machine learning at anywhere at any scale.
Home-page: https://github.com/FedML-AI/FedML
Author: FedML Team
Author-email: ch@fedml.ai
License: Apache 2.0
Keywords: distributed machine learning,federated learning,natural language processing,computer vision,Internet of Things
Platform: UNKNOWN
Classifier: Operating System :: Microsoft :: Windows
Classifier: Operating System :: POSIX
Classifier: Operating System :: Unix
Classifier: Operating System :: MacOS
Classifier: Programming Language :: Python :: 3
Classifier: Programming Language :: Python :: 3.8
Classifier: Programming Language :: Python :: 3.9
Classifier: Programming Language :: Python :: 3.10
Classifier: Programming Language :: Python :: Implementation :: CPython
Classifier: Programming Language :: Python :: Implementation :: PyPy
License-File: LICENSE
Requires-Dist: numpy
Requires-Dist: PyYAML
Requires-Dist: h5py
Requires-Dist: tqdm
Requires-Dist: wget
Requires-Dist: paho-mqtt
Requires-Dist: boto3
Requires-Dist: pynvml
Requires-Dist: sklearn
Requires-Dist: networkx
Requires-Dist: click
Requires-Dist: torch
Requires-Dist: torchvision
Requires-Dist: spacy
Requires-Dist: gensim
Requires-Dist: multiprocess
Requires-Dist: smart-open (==5.2.1)
Requires-Dist: nvidia-ml-py3
Requires-Dist: matplotlib
Requires-Dist: dill
Requires-Dist: pandas
Requires-Dist: wandb (==0.13.2)
Requires-Dist: eciespy
Requires-Dist: MNN (==1.1.6)
Provides-Extra: mpi
Requires-Dist: mpi4py ; extra == 'mpi'
Provides-Extra: grpc
Requires-Dist: grpcio ; extra == 'grpc'
Provides-Extra: jax
Requires-Dist: jax[cpu] ; extra == 'jax'
Requires-Dist: dm-haiku ; extra == 'jax'
Requires-Dist: optax ; extra == 'jax'
Requires-Dist: jaxlib ; extra == 'jax'
Provides-Extra: mxnet
Requires-Dist: mxnet (==2.0.0b1) ; extra == 'mxnet'
Provides-Extra: tensorflow
Requires-Dist: tensorflow ; extra == 'tensorflow'
Requires-Dist: tensorflow-datasets ; extra == 'tensorflow'
Requires-Dist: tensorflow-federated ; extra == 'tensorflow'
